{
	"img": "images/default.png",
	"shorttitle": "Lojban",
	"metadata": {
		"id": "Lojban",
		"title": "The Complete Lojban Language",
		"series": "",
		"sequence": 1,
		"author": "John Woldemar Cowan",
		"fileAs": "Languages",
		"genre": "Non-Fiction",
		"tags": "Lojban",
		"copyright": "John Woldemar Cowan, 2016",
		"publisher": "Logical Language Group",
		"published": "2016-08-26",
		"language": "en",
		"description": "",
		"contents": "Chapters",
		"source": "https://lojban.org/publications/cll/cll_v1.1_xhtml-section-chunks/",
		"images": []
	},
	"titleSelector": "h1, h2.title",
	"contentSelector": ".chapter, .section",
	"urls": [
		"chapter-about.html",
    "section-what-is-cll.html",
    "section-conventions.html",
    "section-disclaimers.html",
    "credits.html",
    "section-bibliography.html",
    "section-captions.html",
    "section-copyright.html",
    "chapter-tour.html",
    "section-pronunciation.html",
    "section-sumti-cmavo.html",
    "section-some-selbri.html",
    "section-some-simple-bridi.html",
    "section-variant-bridi-structure.html",
    "section-order-of-sumti.html",
    "section-structure-of-utterances.html",
    "section-basic-tanru.html",
    "section-description-sumti.html",
    "section-some-brivla.html",
    "section-dihu-and-lahe-dihu.html",
    "section-possession.html",
    "section-vocatives-and-commands.html",
    "section-basic-questions.html",
    "section-attitudinals.html",
    "section-tenses.html",
    "section-terms.html",
    "chapter-phonology.html",
    "section-basic-phonetics.html",
    "section-lojban-characters.html",
    "section-diphthongs.html",
    "section-vowel-pairs.html",
    "section-clusters.html",
    "section-initial-pairs.html",
    "section-buffer-vowels.html",
    "section-stress.html",
    "section-anglophone-phonetics.html",
    "section-anglophone-diphthongs.html",
    "section-oddball-orthographies.html",
    "chapter-morphology.html",
    "section-cmavo.html",
    "section-morphology-brivla.html",
    "section-gismu.html",
    "section-lujvo.html",
    "section-rafsi.html",
    "section-fuhivla.html",
    "section-cmene.html",
    "section-pauses.html",
    "section-lujvo-considerations.html",
    "section-lujvo-making.html",
    "section-lujvo-scoring.html",
    "section-lujvo-making-examples.html",
    "section-gismu-making.html",
    "section-cultural-gismu.html",
    "section-rafsi-fuhivla.html",
    "chapter-selbri.html",
    "section-simple-tanru.html",
    "section-three-part-tanru.html",
    "section-complex-grouping.html",
    "section-ke-grouping.html",
    "section-logical-connection.html",
    "section-be-sumti.html",
    "section-co-inversion.html",
    "section-cmavo-selbri.html",
    "section-me-selbri.html",
    "section-place-conversion.html",
    "section-selbri-scalar-negation.html",
    "section-bridi-negation-tenses.html",
    "section-asymmetric-tanru.html",
    "section-symmetric-tanru.html",
    "section-pretty-school-groupings.html",
    "chapter-sumti.html",
    "section-basic-descriptors.html",
    "section-masses.html",
    "section-sets.html",
    "section-typicals.html",
    "section-quantified-sumti.html",
    "section-quantified-descriptions.html",
    "section-indefinite-descriptions.html",
    "section-sumti-based-descriptions.html",
    "section-sumti-qualifiers.html",
    "section-vocative-syntax.html",
    "section-names.html",
    "section-pro-sumti.html",
    "section-quotation.html",
    "section-number-summary.html",
    "chapter-anaphoric-cmavo.html",
    "section-mi-series.html",
    "section-ti-series.html",
    "section-dihu-series.html",
    "section-koha-broda-series.html",
    "section-ri-gohi-series.html",
    "section-zohe-cohe-series.html",
    "section-voha-series.html",
    "section-sumti-and-bridi-questions.html",
    "section-keha.html",
    "section-cehu.html",
    "section-da-buha-series.html",
    "section-daho.html",
    "section-du.html",
    "section-anaphoric-rafsi.html",
    "section-koha-summary.html",
    "section-goha-summary.html",
    "section-other-summary.html",
    "chapter-relative-clauses.html",
    "section-noi.html",
    "section-relative-phrases.html",
    "section-zihe.html",
    "section-voi.html",
    "section-descriptors.html",
    "section-possessive-sumti.html",
    "section-vuho.html",
    "section-relative-clauses-and-vocatives.html",
    "section-nesting.html",
    "section-relative-clause-cmavo-summary.html",
    "chapter-sumti-tcita.html",
    "section-cu.html",
    "section-FA.html",
    "section-SE.html",
    "section-selbri-modals.html",
    "section-BAI.html",
    "section-causals.html",
    "section-modal-connectives.html",
    "section-modal-selbri.html",
    "section-modal-relative-phrases.html",
    "section-mixed-connection.html",
    "section-modal-jai.html",
    "section-modal-negation.html",
    "section-sticky-modals.html",
    "section-connected-modals.html",
    "section-irregular-BAI.html",
    "section-all-BAI.html",
    "chapter-tenses.html",
    "section-spatial-tenses.html",
    "section-compound-spatial-tenses.html",
    "section-temporal-tenses.html",
    "section-interval-sizes.html",
    "section-vagueness.html",
    "section-dimensionality.html",
    "section-movement.html",
    "section-interval-properties.html",
    "section-event-contours.html",
    "section-fehe.html",
    "section-tcita.html",
    "section-sticky-tenses.html",
    "section-story-time.html",
    "section-sub-bridi-tenses.html",
    "section-tense-connection.html",
    "section-tense-logical-connection.html",
    "section-tense-negation.html",
    "section-caha.html",
    "section-connected-tenses.html",
    "section-sub-events.html",
    "section-jai.html",
    "section-tenses-vs-modals.html",
    "section-tense-questions.html",
    "section-explicit-magnitudes.html",
    "section-exercise.html",
    "section-tense-selmaho-summary.html",
    "section-direction-cmavo.html",
    "chapter-abstractions.html",
    "section-events.html",
    "section-event-types.html",
    "section-properties.html",
    "section-amounts.html",
    "section-truth-values.html",
    "section-predications.html",
    "section-indirect-questions.html",
    "section-minor-abstractions.html",
    "section-sumti-raising.html",
    "section-events-and-contours.html",
    "section-abstractor-connection.html",
    "section-summary.html",
    "chapter-lujvo.html",
    "section-tanru-meanings.html",
    "section-lujvo-meanings.html",
    "section-selecting-places.html",
    "section-symmetrical-asymmetrical.html",
    "section-dependent-places.html",
    "section-order-of-places.html",
    "section-n-part-lujvo.html",
    "section-seltau-SE.html",
    "section-tertau-SE.html",
    "section-eliding-ke-kehe.html",
    "section-abstraction-lujvo.html",
    "section-implicit-abstraction.html",
    "section-anomalous-lujvo.html",
    "section-comparatives.html",
    "section-gismu-place-structures.html",
    "chapter-attitudinals.html",
    "section-pure-emotions.html",
    "section-propositional-emotions.html",
    "section-intensity-scale.html",
    "section-attitudinal-space.html",
    "section-categories.html",
    "section-modifiers.html",
    "section-compound-attitudinals.html",
    "section-scope.html",
    "section-questions-empathy-contours.html",
    "section-evidentials.html",
    "section-discursives.html",
    "section-miscellanious.html",
    "section-vocative-scales.html",
    "section-sample-dialogue.html",
    "section-attitudinals-conclusion.html",
    "chapter-connectives.html",
    "section-four-basics.html",
    "section-six-types.html",
    "section-bridi-connection.html",
    "section-forethought-bridi-connection.html",
    "section-sumti-connection.html",
    "section-more-propositions.html",
    "section-afterthought-connectives-grouping.html",
    "section-compound-bridi.html",
    "section-multiple-compound-bridi.html",
    "section-termsets.html",
    "section-tanru.html",
    "section-truth-and-connective-questions.html",
    "section-non-logical-connectives.html",
    "section-non-logical-continued.html",
    "section-non-logical-continued-continued.html",
    "section-mekso-connections.html",
    "section-sumtcita.html",
    "section-abstractors.html",
    "section-constructs-summary.html",
    "section-truth-functions-summary.html",
    "section-construction-summary.html",
    "section-other-tables.html",
    "chapter-negation.html",
    "section-bridi-negation.html",
    "section-scalar-negation.html",
    "section-nahe.html",
    "section-scales-negation.html",
    "section-sumti-negation.html",
    "section-other-negation.html",
    "section-truth-questions.html",
    "section-affirmations.html",
    "section-metalinguistic-negation.html",
    "section-are-all-questions-answered.html",
    "chapter-quantifiers.html",
    "section-da-and-zohu.html",
    "section-universal-claims.html",
    "section-restricted-claims.html",
    "section-prenex-elision.html",
    "section-quantified-variables.html",
    "section-quantifier-grouping.html",
    "section-any.html",
    "section-negation-boundaries.html",
    "section-connectives.html",
    "section-na-outside-prenex.html",
    "section-demorgans-law.html",
    "section-selbri-variables.html",
    "section-notes-on-variables.html",
    "section-logic-conclusion.html",
    "chapter-letterals.html",
    "section-lerfu-liste.html",
    "section-upper-case.html",
    "section-bu.html",
    "section-alien-alphabets.html",
    "section-accents.html",
    "section-punctuation.html",
    "section-chinese-characters.html",
    "section-lerfu-pro-sumti.html",
    "section-meho.html",
    "section-math.html",
    "section-acronyms.html",
    "section-character-codes.html",
    "section-lerfu-cmavo-summary.html",
    "section-proposed-lerfu-words.html",
    "section-greek.html",
    "section-cyrillic.html",
    "section-hebrew.html",
    "section-accents-multiple-letters.html",
    "section-ICAO-alphabet.html",
    "chapter-mekso.html",
    "section-mekso-numbers.html",
    "section-signs-punctuation.html",
    "section-constants.html",
    "section-simple-infix.html",
    "section-forethought.html",
    "section-useful-selbri.html",
    "section-indefinite-numbers.html",
    "section-approximation.html",
    "section-radixen.html",
    "section-mekso-selbri.html",
    "section-number-questions.html",
    "section-subscripts-math.html",
    "section-infix-again.html",
    "section-vectors-matrices.html",
    "section-reverse-polish-notation.html",
    "section-connectives-within-mekso.html",
    "section-lojban-within-mekso.html",
    "section-other-mekso-uses.html",
    "section-explicit-operator-precedence.html",
    "section-miscellany.html",
    "section-four-score-and-seven.html",
    "section-selmaho-summary.html",
    "section-vuhu.html",
    "section-pa.html",
    "section-moi.html",
    "chapter-structure.html",
    "section-i.html",
    "section-niho.html",
    "section-topic-comments.html",
    "section-questions-and-answers.html",
    "section-subscripts-general.html",
    "section-utterance-ordinals.html",
    "section-attitudinal-scope.html",
    "section-quotations.html",
    "section-more-quotations.html",
    "section-bahe.html",
    "section-parentheses.html",
    "section-erasure.html",
    "section-hesitation.html",
    "section-faho.html",
    "section-cmavo-interactions.html",
    "section-elidable-terminators.html",
    "chapter-catalogue.html",
    "chapter-grammars.html",
    "section-cross-reference.html",
    "go01.html",
    "ix01.html",
    "ix02.html",
    "ix03.html"
	]
}
